conllutils/__init__.py
conllutils/distance.py
conllutils-1.0.0.dist-info/METADATA
conllutils-1.0.0.dist-info/RECORD
conllutils-1.0.0.dist-info/WHEEL
conllutils-1.0.0.dist-info/top_level.txt
