Metadata-Version: 2.1
Name: conllutils
Version: 1.0.0
Summary: Utility classes and functions for parsing and indexing files in CoNLL-U format.
Home-page: https://github.com/peterbednar/conllutils
Author: Peter Bednár
Author-email: peter.bednar@tuke.sk
License: MIT
Platform: UNKNOWN
Requires-Dist: numpy
